pullman.py
pullman-0.9.1.dist-info/LICENSE
pullman-0.9.1.dist-info/METADATA
pullman-0.9.1.dist-info/WHEEL
pullman-0.9.1.dist-info/entry_points.txt
pullman-0.9.1.dist-info/RECORD
