Metadata-Version: 2.1
Name: pullman
Version: 0.9.1
Summary: 🥞 Manage ghstack pull requests 🥞
License: MIT
Author: Tom Ritchford
Author-email: tom@swirly.com
Requires-Python: >=3.9,<4.0
Classifier: License :: OSI Approved :: MIT License
Classifier: Programming Language :: Python :: 3
Classifier: Programming Language :: Python :: 3.9
Classifier: Programming Language :: Python :: 3.10
Classifier: Programming Language :: Python :: 3.11
Classifier: Programming Language :: Python :: 3.12
Classifier: Programming Language :: Python :: 3.13
Requires-Dist: bs4 (>=0.0.2,<0.0.3)
Requires-Dist: requests (>=2.32.3,<3.0.0)
